ashmail/ashmail.py
ashmail/send.py
ashmail-2.1.2.dist-info/LICENSE
ashmail-2.1.2.dist-info/METADATA
ashmail-2.1.2.dist-info/WHEEL
ashmail-2.1.2.dist-info/entry_points.txt
ashmail-2.1.2.dist-info/top_level.txt
ashmail-2.1.2.dist-info/RECORD
