Metadata-Version: 2.1
Name: ashmail
Version: 2.1.2
Summary: the free and simple mass emailing system
Home-page: https://github.com/0x44RU5H/ashmail
Author: Aarush Gupta
Author-email: aarush@theaarushgupta.com
License: AGPLv3+
Platform: UNKNOWN
Classifier: License :: OSI Approved :: GNU Affero General Public License v3 or later (AGPLv3+)
Classifier: Programming Language :: Python :: 3
Classifier: Programming Language :: Python :: 3.8
Requires-Dist: jinja2
Requires-Dist: pyyaml
